KratosMultiphysics/CableNetApplication/__init__.py
KratosMultiphysics/CableNetApplication/apply_weak_sliding_process.py
KratosMultiphysics/CableNetApplication/edge_cable_element_process.py
KratosMultiphysics/CableNetApplication/empirical_spring_element_process.py
KratosMultiphysics/CableNetApplication/sliding_edge_process.py
KratosMultiphysics/.libs/KratosCableNetApplication.cpython-310-x86_64-linux-gnu.so
KratosMultiphysics/.libs/libKratosCableNetCore.so
kratoscablenetapplication-10.4.0.dist-info/METADATA
kratoscablenetapplication-10.4.0.dist-info/WHEEL
kratoscablenetapplication-10.4.0.dist-info/RECORD
